etl_m_ibrahim_khalil/__init__.py
etl_m_ibrahim_khalil/common_utils/__init__.py
etl_m_ibrahim_khalil/common_utils/api_client.py
etl_m_ibrahim_khalil/common_utils/json_encoder.py
etl_m_ibrahim_khalil/config.py
etl_m_ibrahim_khalil/data_sources/__init__.py
etl_m_ibrahim_khalil/data_sources/quotes/__init__.py
etl_m_ibrahim_khalil/data_sources/quotes/constants.py
etl_m_ibrahim_khalil/data_sources/quotes/extractor.py
etl_m_ibrahim_khalil/data_sources/quotes/normalizer.py
etl_m_ibrahim_khalil/data_sources/quotes/transformer.py
etl_m_ibrahim_khalil/models.py
etl_m_ibrahim_khalil/supabase_repository.py
etl_m_ibrahim_khalil-0.0.2.dist-info/LICENSE
etl_m_ibrahim_khalil-0.0.2.dist-info/METADATA
etl_m_ibrahim_khalil-0.0.2.dist-info/WHEEL
etl_m_ibrahim_khalil-0.0.2.dist-info/RECORD
